exp_tool/__init__.py
exp_tool/error_propagation.py
exp_tool/latex_report.py
exp_toolkit_pcp-0.1.0.dist-info/licenses/LICENSE
exp_toolkit_pcp-0.1.0.dist-info/METADATA
exp_toolkit_pcp-0.1.0.dist-info/WHEEL
exp_toolkit_pcp-0.1.0.dist-info/top_level.txt
exp_toolkit_pcp-0.1.0.dist-info/RECORD
