Metadata-Version: 2.4
Name: exp-toolkit-pcp
Version: 0.1.0
Summary: Experimental tools for scientific calculations, including error propagation and LaTeX reporting
Author: Pablo Castro Pérez
Project-URL: Homepage, https://github.com/yourusername/exp_tool
Project-URL: Bug Tracker, https://github.com/yourusername/exp_tool/issues
Requires-Python: >=3.8
License-File: LICENSE
Dynamic: license-file
